<?xml version="1.0" encoding="UTF-8"?>
<!DOCTYPE mapper PUBLIC "-//mybatis.org//DTD Mapper 3.0//EN" "http://mybatis.org/dtd/mybatis-3-mapper.dtd">
<mapper namespace="com.telecomjs.mapper.EopResourceAccessLimitMapper">
  <resultMap id="BaseResultMap" type="com.telecomjs.entities.EopResourceAccessLimit">
    <!--
      WARNING - @mbggenerated
      This element is automatically generated by MyBatis Generator, do not modify.
    -->
    <result column="limit_id" jdbcType="INTEGER" property="limitId" />
    <result column="app_id" jdbcType="INTEGER" property="appId" />
    <result column="domain" jdbcType="VARCHAR" property="domain" />
    <result column="method_name" jdbcType="VARCHAR" property="methodName" />
    <result column="limit_value" jdbcType="INTEGER" property="limitValue" />
    <result column="create_date" jdbcType="DATE" property="createDate" />
  </resultMap>
  <sql id="Base_Column_List">
    limit_id, app_id, domain,
      method_name, limit_value, create_date
  </sql>
  <sql id="Update_By_Example_Where_Clause">
    <!--
      WARNING - @mbggenerated
      This element is automatically generated by MyBatis Generator, do not modify.
    -->
    <where>
      <foreach collection="example.oredCriteria" item="criteria" separator="or">
        <if test="criteria.valid">
          <trim prefix="(" prefixOverrides="and" suffix=")">
            <foreach collection="criteria.criteria" item="criterion">
              <choose>
                <when test="criterion.noValue">
                  and ${criterion.condition}
                </when>
                <when test="criterion.singleValue">
                  and ${criterion.condition} #{criterion.value}
                </when>
                <when test="criterion.betweenValue">
                  and ${criterion.condition} #{criterion.value} and #{criterion.secondValue}
                </when>
                <when test="criterion.listValue">
                  and ${criterion.condition}
                  <foreach close=")" collection="criterion.value" item="listItem" open="(" separator=",">
                    #{listItem}
                  </foreach>
                </when>
              </choose>
            </foreach>
          </trim>
        </if>
      </foreach>
    </where>
  </sql>
  <insert id="insert" parameterType="com.telecomjs.entities.EopResourceAccessLimit">
    <!--
      WARNING - @mbggenerated
      This element is automatically generated by MyBatis Generator, do not modify.
    -->
    insert into eop_resource_access_limit (limit_id, app_id, domain, 
      method_name, limit_value, create_date
      )
    values (#{limitId,jdbcType=INTEGER}, #{appId,jdbcType=INTEGER}, #{domain,jdbcType=VARCHAR}, 
      #{methodName,jdbcType=VARCHAR}, #{limitValue,jdbcType=INTEGER}, #{createDate,jdbcType=DATE}
      )
  </insert>
  <insert id="insertSelective" parameterType="com.telecomjs.entities.EopResourceAccessLimit">
    <!--
      WARNING - @mbggenerated
      This element is automatically generated by MyBatis Generator, do not modify.
    -->
    insert into eop_resource_access_limit
    <trim prefix="(" suffix=")" suffixOverrides=",">
      <if test="limitId != null">
        limit_id,
      </if>
      <if test="appId != null">
        app_id,
      </if>
      <if test="domain != null">
        domain,
      </if>
      <if test="methodName != null">
        method_name,
      </if>
      <if test="limitValue != null">
        limit_value,
      </if>
      <if test="createDate != null">
        create_date,
      </if>
    </trim>
    <trim prefix="values (" suffix=")" suffixOverrides=",">
      <if test="limitId != null">
        #{limitId,jdbcType=INTEGER},
      </if>
      <if test="appId != null">
        #{appId,jdbcType=INTEGER},
      </if>
      <if test="domain != null">
        #{domain,jdbcType=VARCHAR},
      </if>
      <if test="methodName != null">
        #{methodName,jdbcType=VARCHAR},
      </if>
      <if test="limitValue != null">
        #{limitValue,jdbcType=INTEGER},
      </if>
      <if test="createDate != null">
        #{createDate,jdbcType=DATE},
      </if>
    </trim>
  </insert>

  <update id="updateByExampleSelective" parameterType="map">
    <!--
      WARNING - @mbggenerated
      This element is automatically generated by MyBatis Generator, do not modify.
    -->
    update eop_resource_access_limit
    <set>
      <if test="record.limitId != null">
        limit_id = #{record.limitId,jdbcType=INTEGER},
      </if>
      <if test="record.appId != null">
        app_id = #{record.appId,jdbcType=INTEGER},
      </if>
      <if test="record.domain != null">
        domain = #{record.domain,jdbcType=VARCHAR},
      </if>
      <if test="record.methodName != null">
        method_name = #{record.methodName,jdbcType=VARCHAR},
      </if>
      <if test="record.limitValue != null">
        limit_value = #{record.limitValue,jdbcType=INTEGER},
      </if>
      <if test="record.createDate != null">
        create_date = #{record.createDate,jdbcType=DATE},
      </if>
    </set>
    <if test="_parameter != null">
      <include refid="Update_By_Example_Where_Clause" />
    </if>
  </update>
  <update id="updateByExample" parameterType="map">
    <!--
      WARNING - @mbggenerated
      This element is automatically generated by MyBatis Generator, do not modify.
    -->
    update eop_resource_access_limit
    set limit_id = #{record.limitId,jdbcType=INTEGER},
      app_id = #{record.appId,jdbcType=INTEGER},
      domain = #{record.domain,jdbcType=VARCHAR},
      method_name = #{record.methodName,jdbcType=VARCHAR},
      limit_value = #{record.limitValue,jdbcType=INTEGER},
      create_date = #{record.createDate,jdbcType=DATE}
    <if test="_parameter != null">
      <include refid="Update_By_Example_Where_Clause" />
    </if>
  </update>
    <select id="selectByAppId" parameterType="long" resultMap="BaseResultMap">
      SELECT
      <include refid="Base_Column_List" />
      FROM EOP_RESOURCE_ACCESS_LIMIT
      WHERE app_id = #{appId}
      order by method_name
    </select>
</mapper>